com/__init__.py
com/yootk/__init__.py
com/yootk/info/__init__.py
com/yootk/info/message.py
yootk_message_yangrui-0.1.dist-info/METADATA
yootk_message_yangrui-0.1.dist-info/WHEEL
yootk_message_yangrui-0.1.dist-info/top_level.txt
yootk_message_yangrui-0.1.dist-info/RECORD
